[
  {
    "id": "custom-word-bu-rongyi",
    "hanzi": "不容易",
    "pinyin": "bù róngyì",
    "english": "not easy",
    "example_sentence": "学中文<b>不容易</b>。",
    "sentence_pinyin": "",
    "sentence_translation": "",
    "hsk_level": 2,
    "source": "custom",
    "lesson": "2026",
    "notes": "",
    "created_at": "2026-04-19",
    "updated_at": "2026-04-19"
  },
  {
    "id": "custom-word-bu-shufu",
    "hanzi": "不舒服",
    "pinyin": "bù shūfu",
    "english": "not feeling well",
    "example_sentence": "我今天有点<b>不舒服</b>。",
    "sentence_pinyin": "",
    "sentence_translation": "",
    "hsk_level": 2,
    "source": "custom",
    "lesson": "2026",
    "notes": "",
    "created_at": "2026-04-19",
    "updated_at": "2026-04-19"
  },
  {
    "id": "custom-word-chushi",
    "hanzi": "厨师",
    "pinyin": "chúshī",
    "english": "chef",
    "example_sentence": "这位<b>厨师</b>做菜很好吃。",
    "sentence_pinyin": "",
    "sentence_translation": "",
    "hsk_level": 3,
    "source": "custom",
    "lesson": "2026",
    "notes": "",
    "created_at": "2026-04-19",
    "updated_at": "2026-04-19"
  },
  {
    "id": "custom-word-daoshu",
    "hanzi": "倒数",
    "pinyin": "dàoshǔ",
    "english": "to count down",
    "example_sentence": "我们一起<b>倒数</b>三二一。",
    "sentence_pinyin": "",
    "sentence_translation": "",
    "hsk_level": 4,
    "source": "custom",
    "lesson": "2026",
    "notes": "",
    "created_at": "2026-04-19",
    "updated_at": "2026-04-19"
  },
  {
    "id": "custom-word-dingpiao",
    "hanzi": "订票",
    "pinyin": "dìngpiào",
    "english": "to book tickets",
    "example_sentence": "我想在网上<b>订票</b>。",
    "sentence_pinyin": "",
    "sentence_translation": "",
    "hsk_level": 4,
    "source": "custom",
    "lesson": "2026",
    "notes": "",
    "created_at": "2026-04-19",
    "updated_at": "2026-04-19"
  },
  {
    "id": "custom-word-hai-zai-xuexi",
    "hanzi": "还在学习",
    "pinyin": "hái zài xuéxí",
    "english": "still studying",
    "example_sentence": "我<b>还在学习</b>中文。",
    "sentence_pinyin": "",
    "sentence_translation": "",
    "hsk_level": 2,
    "source": "custom",
    "lesson": "2026",
    "notes": "",
    "created_at": "2026-04-19",
    "updated_at": "2026-04-19"
  },
  {
    "id": "custom-word-hen-jin",
    "hanzi": "很近",
    "pinyin": "hěn jìn",
    "english": "very close",
    "example_sentence": "地铁站离这儿<b>很近</b>。",
    "sentence_pinyin": "",
    "sentence_translation": "",
    "hsk_level": 2,
    "source": "custom",
    "lesson": "2026",
    "notes": "",
    "created_at": "2026-04-19",
    "updated_at": "2026-04-19"
  },
  {
    "id": "custom-word-hen-yuan",
    "hanzi": "很远",
    "pinyin": "hěn yuǎn",
    "english": "very far",
    "example_sentence": "学校离我家<b>很远</b>。",
    "sentence_pinyin": "",
    "sentence_translation": "",
    "hsk_level": 2,
    "source": "custom",
    "lesson": "2026",
    "notes": "",
    "created_at": "2026-04-19",
    "updated_at": "2026-04-19"
  },
  {
    "id": "custom-word-jiayou",
    "hanzi": "加油",
    "pinyin": "jiāyóu",
    "english": "come on / keep going / to refuel",
    "example_sentence": "明天考试，<b>加油</b>！",
    "sentence_pinyin": "",
    "sentence_translation": "",
    "hsk_level": 3,
    "source": "custom",
    "lesson": "2026",
    "notes": "",
    "created_at": "2026-04-19",
    "updated_at": "2026-04-19"
  },
  {
    "id": "custom-word-kuai-dao-de-shihou",
    "hanzi": "快到…的时候",
    "pinyin": "kuài dào de shíhou",
    "english": "when it's almost time",
    "example_sentence": "快到上课<b>的时候</b>老师来了。",
    "sentence_pinyin": "",
    "sentence_translation": "",
    "hsk_level": 2,
    "source": "custom",
    "lesson": "2026",
    "notes": "",
    "created_at": "2026-04-19",
    "updated_at": "2026-04-19"
  },
  {
    "id": "custom-word-niupai",
    "hanzi": "牛排",
    "pinyin": "niúpái",
    "english": "steak",
    "example_sentence": "我想吃一份<b>牛排</b>。",
    "sentence_pinyin": "",
    "sentence_translation": "",
    "hsk_level": 4,
    "source": "custom",
    "lesson": "2026",
    "notes": "",
    "created_at": "2026-04-19",
    "updated_at": "2026-04-19"
  },
  {
    "id": "custom-word-niuyouguo",
    "hanzi": "牛油果",
    "pinyin": "niúyóuguǒ",
    "english": "avocado",
    "example_sentence": "我早上吃了一个<b>牛油果</b>。",
    "sentence_pinyin": "",
    "sentence_translation": "",
    "hsk_level": 4,
    "source": "custom",
    "lesson": "2026",
    "notes": "",
    "created_at": "2026-04-19",
    "updated_at": "2026-04-19"
  },
  {
    "id": "custom-word-qian-ji-tian",
    "hanzi": "前几天",
    "pinyin": "qián jǐ tiān",
    "english": "the other day / a few days ago",
    "example_sentence": "我<b>前几天</b>见过他。",
    "sentence_pinyin": "",
    "sentence_translation": "",
    "hsk_level": 2,
    "source": "custom",
    "lesson": "2026",
    "notes": "",
    "created_at": "2026-04-19",
    "updated_at": "2026-04-19"
  },
  {
    "id": "custom-word-qidai",
    "hanzi": "期待",
    "pinyin": "qīdài",
    "english": "to look forward to",
    "example_sentence": "我很<b>期待</b>这次旅行。",
    "sentence_pinyin": "",
    "sentence_translation": "",
    "hsk_level": 4,
    "source": "custom",
    "lesson": "2026",
    "notes": "",
    "created_at": "2026-04-19",
    "updated_at": "2026-04-19"
  },
  {
    "id": "custom-word-shenti-jiankang",
    "hanzi": "身体健康",
    "pinyin": "shēntǐ jiànkāng",
    "english": "good health",
    "example_sentence": "祝你<b>身体健康</b>。",
    "sentence_pinyin": "",
    "sentence_translation": "",
    "hsk_level": 3,
    "source": "custom",
    "lesson": "2026",
    "notes": "",
    "created_at": "2026-04-19",
    "updated_at": "2026-04-19"
  },
  {
    "id": "custom-word-shoudao",
    "hanzi": "收到",
    "pinyin": "shōudào",
    "english": "to receive",
    "example_sentence": "我已经<b>收到</b>你的消息了。",
    "sentence_pinyin": "",
    "sentence_translation": "",
    "hsk_level": 3,
    "source": "custom",
    "lesson": "2026",
    "notes": "",
    "created_at": "2026-04-19",
    "updated_at": "2026-04-19"
  },
  {
    "id": "custom-word-xinwen",
    "hanzi": "新闻",
    "pinyin": "xīnwén",
    "english": "news",
    "example_sentence": "我每天看中文<b>新闻</b>。",
    "sentence_pinyin": "",
    "sentence_translation": "",
    "hsk_level": 2,
    "source": "custom",
    "lesson": "2026",
    "notes": "",
    "created_at": "2026-04-19",
    "updated_at": "2026-04-19"
  },
  {
    "id": "custom-word-xuyao",
    "hanzi": "需要",
    "pinyin": "xūyào",
    "english": "to need / to require",
    "example_sentence": "我<b>需要</b>一杯水。",
    "sentence_pinyin": "",
    "sentence_translation": "",
    "hsk_level": 2,
    "source": "custom",
    "lesson": "2026",
    "notes": "",
    "created_at": "2026-04-19",
    "updated_at": "2026-04-19"
  },
  {
    "id": "custom-word-yanhua",
    "hanzi": "烟花",
    "pinyin": "yānhuā",
    "english": "fireworks",
    "example_sentence": "过年的时候有很多<b>烟花</b>。",
    "sentence_pinyin": "",
    "sentence_translation": "",
    "hsk_level": 4,
    "source": "custom",
    "lesson": "2026",
    "notes": "",
    "created_at": "2026-04-19",
    "updated_at": "2026-04-19"
  },
  {
    "id": "custom-word-yi-dao-jiu",
    "hanzi": "一到…就…",
    "pinyin": "yí dào jiù…",
    "english": "as soon as…",
    "example_sentence": "他<b>一到</b>家<b>就</b>睡觉。",
    "sentence_pinyin": "",
    "sentence_translation": "",
    "hsk_level": 3,
    "source": "custom",
    "lesson": "2026",
    "notes": "",
    "created_at": "2026-04-19",
    "updated_at": "2026-04-19"
  },
  {
    "id": "custom-word-you-kong",
    "hanzi": "有空",
    "pinyin": "yǒu kòng",
    "english": "to have free time",
    "example_sentence": "你明天<b>有空</b>吗？",
    "sentence_pinyin": "",
    "sentence_translation": "",
    "hsk_level": 2,
    "source": "custom",
    "lesson": "2026",
    "notes": "",
    "created_at": "2026-04-19",
    "updated_at": "2026-04-19"
  },
  {
    "id": "custom-word-zhu",
    "hanzi": "祝",
    "pinyin": "zhù",
    "english": "to wish",
    "example_sentence": "<b>祝</b>你生日快乐。",
    "sentence_pinyin": "",
    "sentence_translation": "",
    "hsk_level": 3,
    "source": "custom",
    "lesson": "2026",
    "notes": "",
    "created_at": "2026-04-19",
    "updated_at": "2026-04-19"
  },
  {
    "id": "custom-word-difang",
    "hanzi": "地方",
    "pinyin": "dìfāng",
    "english": "place",
    "example_sentence": "这个<b>地方</b>很安静。",
    "sentence_pinyin": "",
    "sentence_translation": "",
    "hsk_level": 2,
    "source": "custom",
    "lesson": "2026",
    "notes": "",
    "created_at": "2026-04-21",
    "updated_at": "2026-04-21"
  },
  {
    "id": "custom-word-paizhao",
    "hanzi": "拍照",
    "pinyin": "pāizhào",
    "english": "to take photos",
    "example_sentence": "我们在这里<b>拍照</b>吧。",
    "sentence_pinyin": "",
    "sentence_translation": "",
    "hsk_level": 3,
    "source": "custom",
    "lesson": "2026",
    "notes": "",
    "created_at": "2026-04-21",
    "updated_at": "2026-04-21"
  },
  {
    "id": "custom-word-zhaogu",
    "hanzi": "照顾",
    "pinyin": "zhàogù",
    "english": "to take care of",
    "example_sentence": "她每天<b>照顾</b>孩子。",
    "sentence_pinyin": "",
    "sentence_translation": "",
    "hsk_level": 4,
    "source": "custom",
    "lesson": "2026",
    "notes": "",
    "created_at": "2026-04-21",
    "updated_at": "2026-04-21"
  },
  {
    "id": "custom-word-zuoye",
    "hanzi": "作业",
    "pinyin": "zuòyè",
    "english": "homework",
    "example_sentence": "我今天晚上要做<b>作业</b>。",
    "sentence_pinyin": "",
    "sentence_translation": "",
    "hsk_level": 2,
    "source": "custom",
    "lesson": "2026",
    "notes": "",
    "created_at": "2026-04-24",
    "updated_at": "2026-04-24"
  },
  {
    "id": "custom-word-ganmao",
    "hanzi": "感冒",
    "pinyin": "gǎnmào",
    "english": "to catch a cold / a cold",
    "example_sentence": "我昨天<b>感冒</b>了。",
    "sentence_pinyin": "",
    "sentence_translation": "",
    "hsk_level": 3,
    "source": "custom",
    "lesson": "2026",
    "notes": "",
    "created_at": "2026-04-24",
    "updated_at": "2026-04-24"
  },
  {
    "id": "custom-word-shaozi",
    "hanzi": "勺子",
    "pinyin": "sháozi",
    "english": "spoon",
    "example_sentence": "我用<b>勺子</b>喝汤。",
    "sentence_pinyin": "",
    "sentence_translation": "",
    "hsk_level": 4,
    "source": "custom",
    "lesson": "2026",
    "notes": "",
    "created_at": "2026-04-24",
    "updated_at": "2026-04-24"
  },
  {
    "id": "custom-word-chazi",
    "hanzi": "叉子",
    "pinyin": "chāzi",
    "english": "fork",
    "example_sentence": "请给我一个<b>叉子</b>。",
    "sentence_pinyin": "",
    "sentence_translation": "",
    "hsk_level": 4,
    "source": "custom",
    "lesson": "2026",
    "notes": "",
    "created_at": "2026-04-24",
    "updated_at": "2026-04-24"
  },
  {
    "id": "custom-word-daozi",
    "hanzi": "刀子",
    "pinyin": "dāozi",
    "english": "knife",
    "example_sentence": "这把<b>刀子</b>很小。",
    "sentence_pinyin": "",
    "sentence_translation": "",
    "hsk_level": 4,
    "source": "custom",
    "lesson": "2026",
    "notes": "",
    "created_at": "2026-04-24",
    "updated_at": "2026-04-24"
  },
  {
    "id": "custom-word-kuaizi",
    "hanzi": "筷子",
    "pinyin": "kuàizi",
    "english": "chopsticks",
    "example_sentence": "我会用<b>筷子</b>吃饭。",
    "sentence_pinyin": "",
    "sentence_translation": "",
    "hsk_level": 4,
    "source": "custom",
    "lesson": "2026",
    "notes": "",
    "created_at": "2026-04-24",
    "updated_at": "2026-04-24"
  },
  {
    "id": "custom-word-tangshao",
    "hanzi": "汤勺",
    "pinyin": "tāngsháo",
    "english": "soup spoon / ladle spoon",
    "example_sentence": "请给我一个<b>汤勺</b>。",
    "sentence_pinyin": "",
    "sentence_translation": "",
    "hsk_level": 5,
    "source": "custom",
    "lesson": "2026",
    "notes": "",
    "created_at": "2026-04-24",
    "updated_at": "2026-04-24"
  },
  {
    "id": "custom-word-chachi",
    "hanzi": "茶匙",
    "pinyin": "cháchí",
    "english": "teaspoon",
    "example_sentence": "咖啡里放一<b>茶匙</b>糖。",
    "sentence_pinyin": "",
    "sentence_translation": "",
    "hsk_level": 5,
    "source": "custom",
    "lesson": "2026",
    "notes": "",
    "created_at": "2026-04-24",
    "updated_at": "2026-04-24"
  },
  {
    "id": "custom-word-tianpincha",
    "hanzi": "甜品叉",
    "pinyin": "tiánpǐnchā",
    "english": "dessert fork",
    "example_sentence": "我用<b>甜品叉</b>吃蛋糕。",
    "sentence_pinyin": "",
    "sentence_translation": "",
    "hsk_level": 5,
    "source": "custom",
    "lesson": "2026",
    "notes": "",
    "created_at": "2026-04-24",
    "updated_at": "2026-04-24"
  },
  {
    "id": "custom-word-huangyoudao",
    "hanzi": "黄油刀",
    "pinyin": "huángyóudāo",
    "english": "butter knife",
    "example_sentence": "桌上有一把<b>黄油刀</b>。",
    "sentence_pinyin": "",
    "sentence_translation": "",
    "hsk_level": 5,
    "source": "custom",
    "lesson": "2026",
    "notes": "",
    "created_at": "2026-04-24",
    "updated_at": "2026-04-24"
  },
  {
    "id": "custom-word-pisadao",
    "hanzi": "披萨刀",
    "pinyin": "pīsàdāo",
    "english": "pizza cutter / pizza knife",
    "example_sentence": "我找不到<b>披萨刀</b>了。",
    "sentence_pinyin": "",
    "sentence_translation": "",
    "hsk_level": 5,
    "source": "custom",
    "lesson": "2026",
    "notes": "",
    "created_at": "2026-04-24",
    "updated_at": "2026-04-24"
  },
  {
    "id": "custom-word-canju",
    "hanzi": "餐具",
    "pinyin": "cānjù",
    "english": "tableware / cutlery",
    "example_sentence": "这些<b>餐具</b>很干净。",
    "sentence_pinyin": "",
    "sentence_translation": "",
    "hsk_level": 4,
    "source": "custom",
    "lesson": "2026",
    "notes": "",
    "created_at": "2026-04-24",
    "updated_at": "2026-04-24"
  },
  {
    "id": "custom-word-kaixin",
    "hanzi": "开心",
    "pinyin": "kāixīn",
    "english": "happy / glad",
    "example_sentence": "听到这个消息我很<b>开心</b>。",
    "sentence_pinyin": "",
    "sentence_translation": "",
    "hsk_level": 2,
    "source": "custom",
    "lesson": "2026",
    "notes": "",
    "created_at": "2026-04-24",
    "updated_at": "2026-04-24"
  },
  {
    "id": "custom-word-jie-dianhua",
    "hanzi": "接电话",
    "pinyin": "jiē diànhuà",
    "english": "to answer the phone",
    "example_sentence": "他在开会，不能<b>接电话</b>。",
    "sentence_pinyin": "",
    "sentence_translation": "",
    "hsk_level": 3,
    "source": "custom",
    "lesson": "2026",
    "notes": "",
    "created_at": "2026-04-24",
    "updated_at": "2026-04-24"
  },
  {
    "id": "custom-word-gua-dianhua",
    "hanzi": "挂电话",
    "pinyin": "guà diànhuà",
    "english": "to hang up the phone",
    "example_sentence": "我先<b>挂电话</b>了。",
    "sentence_pinyin": "",
    "sentence_translation": "",
    "hsk_level": 4,
    "source": "custom",
    "lesson": "2026",
    "notes": "",
    "created_at": "2026-04-24",
    "updated_at": "2026-04-24"
  },
  {
    "id": "custom-word-yihou",
    "hanzi": "以后",
    "pinyin": "yǐhòu",
    "english": "afterwards / later / in the future",
    "example_sentence": "我们<b>以后</b>再聊吧。",
    "sentence_pinyin": "",
    "sentence_translation": "",
    "hsk_level": 3,
    "source": "custom",
    "lesson": "2026",
    "notes": "",
    "created_at": "2026-04-24",
    "updated_at": "2026-04-24"
  },
  {
    "id": "custom-word-ranhou",
    "hanzi": "然后",
    "pinyin": "ránhòu",
    "english": "then / after that",
    "example_sentence": "他先吃饭，<b>然后</b>去上班。",
    "sentence_pinyin": "",
    "sentence_translation": "",
    "hsk_level": 2,
    "source": "custom",
    "lesson": "2026",
    "notes": "",
    "created_at": "2026-04-24",
    "updated_at": "2026-04-24"
  },
  {
    "id": "custom-word-zuijin",
    "hanzi": "最近",
    "pinyin": "zuìjìn",
    "english": "recently / lately",
    "example_sentence": "我<b>最近</b>很忙。",
    "sentence_pinyin": "",
    "sentence_translation": "",
    "hsk_level": 3,
    "source": "custom",
    "lesson": "2026",
    "notes": "",
    "created_at": "2026-04-24",
    "updated_at": "2026-04-24"
  },
  {
    "id": "custom-word-hai-xing",
    "hanzi": "还行",
    "pinyin": "hái xíng",
    "english": "not bad / okay",
    "example_sentence": "这个菜的味道<b>还行</b>。",
    "sentence_pinyin": "",
    "sentence_translation": "",
    "hsk_level": 3,
    "source": "custom",
    "lesson": "2026",
    "notes": "",
    "created_at": "2026-04-24",
    "updated_at": "2026-04-24"
  },
  {
    "id": "custom-word-dasuan",
    "hanzi": "打算",
    "pinyin": "dǎsuàn",
    "english": "to plan / to intend",
    "example_sentence": "我<b>打算</b>明年去中国。",
    "sentence_pinyin": "",
    "sentence_translation": "",
    "hsk_level": 3,
    "source": "custom",
    "lesson": "2026",
    "notes": "",
    "created_at": "2026-04-24",
    "updated_at": "2026-04-24"
  },
  {
    "id": "custom-word-zhoumo",
    "hanzi": "周末",
    "pinyin": "zhōumò",
    "english": "weekend",
    "example_sentence": "<b>周末</b>我想在家休息。",
    "sentence_pinyin": "",
    "sentence_translation": "",
    "hsk_level": 3,
    "source": "custom",
    "lesson": "2026",
    "notes": "",
    "created_at": "2026-04-24",
    "updated_at": "2026-04-24"
  },
  {
    "id": "custom-word-gongli",
    "hanzi": "公里",
    "pinyin": "gōnglǐ",
    "english": "kilometer",
    "example_sentence": "我家离公司五<b>公里</b>。",
    "sentence_pinyin": "",
    "sentence_translation": "",
    "hsk_level": 4,
    "source": "custom",
    "lesson": "2026",
    "notes": "",
    "created_at": "2026-04-24",
    "updated_at": "2026-04-24"
  },
  {
    "id": "custom-word-limi",
    "hanzi": "厘米",
    "pinyin": "límǐ",
    "english": "centimeter",
    "example_sentence": "这张纸长三十<b>厘米</b>。",
    "sentence_pinyin": "",
    "sentence_translation": "",
    "hsk_level": 4,
    "source": "custom",
    "lesson": "2026",
    "notes": "",
    "created_at": "2026-04-24",
    "updated_at": "2026-04-24"
  },
  {
    "id": "custom-word-zhaodao",
    "hanzi": "找到",
    "pinyin": "zhǎodào",
    "english": "to find / to locate",
    "example_sentence": "我终于<b>找到</b>钥匙了。",
    "sentence_pinyin": "",
    "sentence_translation": "",
    "hsk_level": 2,
    "source": "custom",
    "lesson": "2026",
    "notes": "",
    "created_at": "2026-04-24",
    "updated_at": "2026-04-24"
  },
  {
    "id": "custom-word-bangzhu",
    "hanzi": "帮助",
    "pinyin": "bāngzhù",
    "english": "to help / help",
    "example_sentence": "你可以<b>帮助</b>我吗？",
    "sentence_pinyin": "",
    "sentence_translation": "",
    "hsk_level": 3,
    "source": "custom",
    "lesson": "2026",
    "notes": "",
    "created_at": "2026-04-24",
    "updated_at": "2026-04-24"
  },
  {
    "id": "custom-word-dianzi-yinyue",
    "hanzi": "电子音乐",
    "pinyin": "diànzǐ yīnyuè",
    "english": "electronic music",
    "example_sentence": "他很喜欢听<b>电子音乐</b>。",
    "sentence_pinyin": "",
    "sentence_translation": "",
    "hsk_level": 5,
    "source": "custom",
    "lesson": "2026",
    "notes": "",
    "created_at": "2026-04-24",
    "updated_at": "2026-04-24"
  },
  {
    "id": "custom-word-fa-duanxin",
    "hanzi": "发短信",
    "pinyin": "fā duǎnxìn",
    "english": "to send a text message",
    "example_sentence": "我先给他<b>发短信</b>。",
    "sentence_pinyin": "",
    "sentence_translation": "",
    "hsk_level": 4,
    "source": "custom",
    "lesson": "2026",
    "notes": "",
    "created_at": "2026-04-24",
    "updated_at": "2026-04-24"
  },
  {
    "id": "custom-word-yi-shuang-xie",
    "hanzi": "一双鞋",
    "pinyin": "yì shuāng xié",
    "english": "a pair of shoes",
    "example_sentence": "我想买<b>一双鞋</b>。",
    "sentence_pinyin": "",
    "sentence_translation": "",
    "hsk_level": 2,
    "source": "custom",
    "lesson": "2026",
    "notes": "",
    "created_at": "2026-04-24",
    "updated_at": "2026-04-24"
  },
  {
    "id": "custom-word-tan-gangqin",
    "hanzi": "弹钢琴",
    "pinyin": "tán gāngqín",
    "english": "to play the piano",
    "example_sentence": "她从小就会<b>弹钢琴</b>。",
    "sentence_pinyin": "",
    "sentence_translation": "",
    "hsk_level": 4,
    "source": "custom",
    "lesson": "2026",
    "notes": "",
    "created_at": "2026-04-24",
    "updated_at": "2026-04-24"
  },
  {
    "id": "custom-word-laogong",
    "hanzi": "老公",
    "pinyin": "lǎogōng",
    "english": "husband",
    "example_sentence": "我<b>老公</b>今天在家工作。",
    "sentence_pinyin": "",
    "sentence_translation": "",
    "hsk_level": 3,
    "source": "custom",
    "lesson": "2026",
    "notes": "",
    "created_at": "2026-04-24",
    "updated_at": "2026-04-24"
  },
  {
    "id": "custom-word-laopo",
    "hanzi": "老婆",
    "pinyin": "lǎopó",
    "english": "wife",
    "example_sentence": "我<b>老婆</b>喜欢喝茶。",
    "sentence_pinyin": "",
    "sentence_translation": "",
    "hsk_level": 3,
    "source": "custom",
    "lesson": "2026",
    "notes": "",
    "created_at": "2026-04-24",
    "updated_at": "2026-04-24"
  },
  {
    "id": "custom-word-fuqi",
    "hanzi": "夫妻",
    "pinyin": "fūqī",
    "english": "married couple / spouses",
    "example_sentence": "他们是一对年轻<b>夫妻</b>。",
    "sentence_pinyin": "",
    "sentence_translation": "",
    "hsk_level": 4,
    "source": "custom",
    "lesson": "2026",
    "notes": "",
    "created_at": "2026-04-24",
    "updated_at": "2026-04-24"
  },
  {
    "id": "custom-word-niurou",
    "hanzi": "牛肉",
    "pinyin": "niúròu",
    "english": "beef",
    "example_sentence": "今天晚上我们吃<b>牛肉</b>。",
    "sentence_pinyin": "",
    "sentence_translation": "",
    "hsk_level": 2,
    "source": "custom",
    "lesson": "2026",
    "notes": "",
    "created_at": "2026-04-24",
    "updated_at": "2026-04-24"
  },
  {
    "id": "custom-word-zhijin",
    "hanzi": "纸巾",
    "pinyin": "zhǐjīn",
    "english": "tissue / napkin",
    "example_sentence": "服务员，我需要<b>纸巾</b>。",
    "sentence_pinyin": "",
    "sentence_translation": "",
    "hsk_level": 4,
    "source": "custom",
    "lesson": "2026",
    "notes": "",
    "created_at": "2026-04-24",
    "updated_at": "2026-04-24"
  },
  {
    "id": "custom-word-putonghua",
    "hanzi": "普通话",
    "pinyin": "pǔtōnghuà",
    "english": "Mandarin Chinese",
    "example_sentence": "我想说好<b>普通话</b>。",
    "sentence_pinyin": "",
    "sentence_translation": "",
    "hsk_level": 4,
    "source": "custom",
    "lesson": "2026",
    "notes": "",
    "created_at": "2026-04-24",
    "updated_at": "2026-04-24"
  },
  {
    "id": "custom-word-tushuguan",
    "hanzi": "图书馆",
    "pinyin": "túshūguǎn",
    "english": "library",
    "example_sentence": "周末我去<b>图书馆</b>看书。",
    "sentence_pinyin": "",
    "sentence_translation": "",
    "hsk_level": 4,
    "source": "custom",
    "lesson": "2026",
    "notes": "",
    "created_at": "2026-04-24",
    "updated_at": "2026-04-24"
  },
  {
    "id": "custom-word-cai",
    "hanzi": "才",
    "pinyin": "cái",
    "english": "only / not until",
    "example_sentence": "他昨天晚上十点<b>才</b>回家。",
    "sentence_pinyin": "",
    "sentence_translation": "",
    "hsk_level": 3,
    "source": "custom",
    "lesson": "2026",
    "notes": "",
    "created_at": "2026-04-24",
    "updated_at": "2026-04-24"
  },
  {
    "id": "custom-word-gongxi-facai",
    "hanzi": "恭喜发财",
    "pinyin": "gōngxǐ fācái",
    "english": "wish you prosperity",
    "example_sentence": "过年的时候我们会说“<b>恭喜发财</b>”。",
    "sentence_pinyin": "",
    "sentence_translation": "",
    "hsk_level": 5,
    "source": "custom",
    "lesson": "2026",
    "notes": "",
    "created_at": "2026-04-24",
    "updated_at": "2026-04-24"
  },
  {
    "id": "custom-word-jiaban",
    "hanzi": "加班",
    "pinyin": "jiābān",
    "english": "to work overtime",
    "example_sentence": "我老公今天晚上又要<b>加班</b>。",
    "sentence_pinyin": "",
    "sentence_translation": "",
    "hsk_level": 4,
    "source": "custom",
    "lesson": "2026",
    "notes": "",
    "created_at": "2026-04-24",
    "updated_at": "2026-04-24"
  },
  {
    "id": "custom-word-gongjin",
    "hanzi": "公斤",
    "pinyin": "gōngjīn",
    "english": "kilogram",
    "example_sentence": "这个西瓜有五<b>公斤</b>。",
    "sentence_pinyin": "",
    "sentence_translation": "",
    "hsk_level": 3,
    "source": "custom",
    "lesson": "2026",
    "notes": "",
    "created_at": "2026-04-24",
    "updated_at": "2026-04-24"
  },
  {
    "id": "custom-word-chuyuan",
    "hanzi": "出院",
    "pinyin": "chūyuàn",
    "english": "to leave the hospital / be discharged",
    "example_sentence": "爷爷明天可以<b>出院</b>了。",
    "sentence_pinyin": "",
    "sentence_translation": "",
    "hsk_level": 4,
    "source": "custom",
    "lesson": "2026",
    "notes": "",
    "created_at": "2026-04-24",
    "updated_at": "2026-04-24"
  },
  {
    "id": "custom-word-zai-shuo-yi-bian",
    "hanzi": "再说一遍",
    "pinyin": "zài shuō yí biàn",
    "english": "say it again / repeat that",
    "example_sentence": "请你<b>再说一遍</b>。",
    "sentence_pinyin": "",
    "sentence_translation": "",
    "hsk_level": 3,
    "source": "custom",
    "lesson": "2026",
    "notes": "",
    "created_at": "2026-04-24",
    "updated_at": "2026-04-24"
  },
  {
    "id": "custom-word-buyong",
    "hanzi": "不用",
    "pinyin": "búyòng",
    "english": "no need to / not necessary",
    "example_sentence": "你今天<b>不用</b>来学校。",
    "sentence_pinyin": "",
    "sentence_translation": "",
    "hsk_level": 2,
    "source": "custom",
    "lesson": "2026",
    "notes": "",
    "created_at": "2026-04-24",
    "updated_at": "2026-04-24"
  },
  {
    "id": "custom-word-zhishi",
    "hanzi": "只是",
    "pinyin": "zhǐshì",
    "english": "only / merely / just",
    "example_sentence": "我<b>只是</b>想问一个问题。",
    "sentence_pinyin": "",
    "sentence_translation": "",
    "hsk_level": 3,
    "source": "custom",
    "lesson": "2026",
    "notes": "",
    "created_at": "2026-04-24",
    "updated_at": "2026-04-24"
  },
  {
    "id": "custom-word-keqi",
    "hanzi": "客气",
    "pinyin": "kèqi",
    "english": "polite / courteous",
    "example_sentence": "你太<b>客气</b>了。",
    "sentence_pinyin": "",
    "sentence_translation": "",
    "hsk_level": 3,
    "source": "custom",
    "lesson": "2026",
    "notes": "",
    "created_at": "2026-04-24",
    "updated_at": "2026-04-24"
  },
  {
    "id": "custom-word-yaoqing",
    "hanzi": "邀请",
    "pinyin": "yāoqǐng",
    "english": "to invite",
    "example_sentence": "我想<b>邀请</b>你来我家吃饭。",
    "sentence_pinyin": "",
    "sentence_translation": "",
    "hsk_level": 4,
    "source": "custom",
    "lesson": "2026",
    "notes": "",
    "created_at": "2026-04-24",
    "updated_at": "2026-04-24"
  },
  {
    "id": "custom-word-ping",
    "hanzi": "瓶",
    "pinyin": "píng",
    "english": "bottle; classifier for bottled things",
    "example_sentence": "我买了一<b>瓶</b>水。",
    "sentence_pinyin": "",
    "sentence_translation": "",
    "hsk_level": 3,
    "source": "custom",
    "lesson": "2026",
    "notes": "",
    "created_at": "2026-04-24",
    "updated_at": "2026-04-24"
  },
  {
    "id": "custom-word-qianbi",
    "hanzi": "铅笔",
    "pinyin": "qiānbǐ",
    "english": "pencil",
    "example_sentence": "桌子上有一支<b>铅笔</b>。",
    "sentence_pinyin": "",
    "sentence_translation": "",
    "hsk_level": 3,
    "source": "custom",
    "lesson": "2026",
    "notes": "",
    "created_at": "2026-04-24",
    "updated_at": "2026-04-24"
  },
  {
    "id": "custom-word-changge",
    "hanzi": "唱歌",
    "pinyin": "chànggē",
    "english": "to sing",
    "example_sentence": "我妹妹很喜欢<b>唱歌</b>。",
    "sentence_pinyin": "",
    "sentence_translation": "",
    "hsk_level": 2,
    "source": "custom",
    "lesson": "2026",
    "notes": "",
    "created_at": "2026-04-24",
    "updated_at": "2026-04-24"
  },
  {
    "id": "custom-word-baozhi",
    "hanzi": "报纸",
    "pinyin": "bàozhǐ",
    "english": "newspaper",
    "example_sentence": "爷爷每天早上看<b>报纸</b>。",
    "sentence_pinyin": "",
    "sentence_translation": "",
    "hsk_level": 3,
    "source": "custom",
    "lesson": "2026",
    "notes": "",
    "created_at": "2026-04-24",
    "updated_at": "2026-04-24"
  },
  {
    "id": "custom-word-shengqi",
    "hanzi": "生气",
    "pinyin": "shēngqì",
    "english": "to get angry / angry",
    "example_sentence": "妈妈知道以后没有<b>生气</b>。",
    "sentence_pinyin": "",
    "sentence_translation": "",
    "hsk_level": 3,
    "source": "custom",
    "lesson": "2026",
    "notes": "",
    "created_at": "2026-04-24",
    "updated_at": "2026-04-24"
  },
  {
    "id": "custom-word-sanbu",
    "hanzi": "散步",
    "pinyin": "sànbù",
    "english": "to take a walk",
    "example_sentence": "晚饭后我们去公园<b>散步</b>。",
    "sentence_pinyin": "",
    "sentence_translation": "",
    "hsk_level": 3,
    "source": "custom",
    "lesson": "2026",
    "notes": "",
    "created_at": "2026-04-24",
    "updated_at": "2026-04-24"
  },
  {
    "id": "custom-word-yiqian",
    "hanzi": "以前",
    "pinyin": "yǐqián",
    "english": "before / formerly",
    "example_sentence": "我<b>以前</b>住在新加坡。",
    "sentence_pinyin": "",
    "sentence_translation": "",
    "hsk_level": 3,
    "source": "custom",
    "lesson": "2026",
    "notes": "",
    "created_at": "2026-04-24",
    "updated_at": "2026-04-24"
  },
  {
    "id": "custom-word-jiankang",
    "hanzi": "健康",
    "pinyin": "jiànkāng",
    "english": "healthy / health",
    "example_sentence": "我希望家人都很<b>健康</b>。",
    "sentence_pinyin": "",
    "sentence_translation": "",
    "hsk_level": 3,
    "source": "custom",
    "lesson": "2026",
    "notes": "",
    "created_at": "2026-04-24",
    "updated_at": "2026-04-24"
  },
  {
    "id": "custom-word-tingdao",
    "hanzi": "听到",
    "pinyin": "tīngdào",
    "english": "to hear",
    "example_sentence": "我在门外<b>听到</b>他的声音。",
    "sentence_pinyin": "",
    "sentence_translation": "",
    "hsk_level": 3,
    "source": "custom",
    "lesson": "2026",
    "notes": "",
    "created_at": "2026-04-24",
    "updated_at": "2026-04-24"
  },
  {
    "id": "custom-word-shenghuo",
    "hanzi": "生活",
    "pinyin": "shēnghuó",
    "english": "life / to live",
    "example_sentence": "我喜欢现在的<b>生活</b>。",
    "sentence_pinyin": "",
    "sentence_translation": "",
    "hsk_level": 3,
    "source": "custom",
    "lesson": "2026",
    "notes": "",
    "created_at": "2026-04-24",
    "updated_at": "2026-04-24"
  },
  {
    "id": "custom-word-wukelanyu",
    "hanzi": "乌克兰语",
    "pinyin": "Wūkèlányǔ",
    "english": "Ukrainian language",
    "example_sentence": "我会说<b>乌克兰语</b>。",
    "sentence_pinyin": "",
    "sentence_translation": "",
    "hsk_level": 5,
    "source": "custom",
    "lesson": "2026",
    "notes": "",
    "created_at": "2026-04-24",
    "updated_at": "2026-04-24"
  },
  {
    "id": "custom-word-zixingche",
    "hanzi": "自行车",
    "pinyin": "zìxíngchē",
    "english": "bicycle",
    "example_sentence": "他每天骑<b>自行车</b>去学校。",
    "sentence_pinyin": "",
    "sentence_translation": "",
    "hsk_level": 3,
    "source": "custom",
    "lesson": "2026",
    "notes": "",
    "created_at": "2026-04-24",
    "updated_at": "2026-04-24"
  },
  {
    "id": "custom-word-miantiao",
    "hanzi": "面条",
    "pinyin": "miàntiáo",
    "english": "noodles",
    "example_sentence": "今天晚上我想吃<b>面条</b>。",
    "sentence_pinyin": "",
    "sentence_translation": "",
    "hsk_level": 3,
    "source": "custom",
    "lesson": "2026",
    "notes": "",
    "created_at": "2026-04-24",
    "updated_at": "2026-04-24"
  },
  {
    "id": "custom-word-bugai",
    "hanzi": "不该",
    "pinyin": "bùgāi",
    "english": "should not / ought not to",
    "example_sentence": "我昨天<b>不该</b>睡那么晚。",
    "sentence_pinyin": "",
    "sentence_translation": "",
    "hsk_level": 4,
    "source": "custom",
    "lesson": "2026",
    "notes": "",
    "created_at": "2026-04-24",
    "updated_at": "2026-04-24"
  },
  {
    "id": "custom-word-mingbai",
    "hanzi": "明白",
    "pinyin": "míngbai",
    "english": "to understand / clear",
    "example_sentence": "老师一解释，我就<b>明白</b>了。",
    "sentence_pinyin": "",
    "sentence_translation": "",
    "hsk_level": 3,
    "source": "custom",
    "lesson": "2026",
    "notes": "",
    "created_at": "2026-04-24",
    "updated_at": "2026-04-24"
  },
  {
    "id": "custom-word-fa-xiaoxi",
    "hanzi": "发消息",
    "pinyin": "fā xiāoxi",
    "english": "to send a message",
    "example_sentence": "我先给老师<b>发消息</b>。",
    "sentence_pinyin": "",
    "sentence_translation": "",
    "hsk_level": 4,
    "source": "custom",
    "lesson": "2026",
    "notes": "",
    "created_at": "2026-04-24",
    "updated_at": "2026-04-24"
  },
  {
    "id": "custom-word-sushe",
    "hanzi": "宿舍",
    "pinyin": "sùshè",
    "english": "dormitory / dorm room",
    "example_sentence": "他晚上回<b>宿舍</b>了。",
    "sentence_pinyin": "",
    "sentence_translation": "",
    "hsk_level": 4,
    "source": "custom",
    "lesson": "2026",
    "notes": "",
    "created_at": "2026-04-24",
    "updated_at": "2026-04-24"
  },
  {
    "id": "custom-word-gongyuan",
    "hanzi": "公园",
    "pinyin": "gōngyuán",
    "english": "park",
    "example_sentence": "孩子们在<b>公园</b>玩儿。",
    "sentence_pinyin": "",
    "sentence_translation": "",
    "hsk_level": 2,
    "source": "custom",
    "lesson": "2026",
    "notes": "",
    "created_at": "2026-04-24",
    "updated_at": "2026-04-24"
  },
  {
    "id": "custom-word-bangongshi",
    "hanzi": "办公室",
    "pinyin": "bàngōngshì",
    "english": "office",
    "example_sentence": "王老师现在在<b>办公室</b>。",
    "sentence_pinyin": "",
    "sentence_translation": "",
    "hsk_level": 4,
    "source": "custom",
    "lesson": "2026",
    "notes": "",
    "created_at": "2026-04-24",
    "updated_at": "2026-04-24"
  },
  {
    "id": "custom-word-qiantai",
    "hanzi": "前台",
    "pinyin": "qiántái",
    "english": "front desk / reception",
    "example_sentence": "你可以先去<b>前台</b>问一下。",
    "sentence_pinyin": "",
    "sentence_translation": "",
    "hsk_level": 4,
    "source": "custom",
    "lesson": "2026",
    "notes": "",
    "created_at": "2026-04-24",
    "updated_at": "2026-04-24"
  },
  {
    "id": "custom-word-shenme-dou",
    "hanzi": "什么都",
    "pinyin": "shénme dōu",
    "english": "everything / anything",
    "example_sentence": "今天我<b>什么都</b>不想做。",
    "sentence_pinyin": "",
    "sentence_translation": "",
    "hsk_level": 2,
    "source": "custom",
    "lesson": "2026",
    "notes": "",
    "created_at": "2026-04-29",
    "updated_at": "2026-04-29"
  },
  {
    "id": "custom-word-gongchengshi",
    "hanzi": "工程师",
    "pinyin": "gōngchéngshī",
    "english": "engineer",
    "example_sentence": "我哥哥是<b>工程师</b>。",
    "sentence_pinyin": "",
    "sentence_translation": "",
    "hsk_level": 4,
    "source": "custom",
    "lesson": "2026",
    "notes": "",
    "created_at": "2026-04-29",
    "updated_at": "2026-04-29"
  },
  {
    "id": "custom-word-gang-dao",
    "hanzi": "刚到",
    "pinyin": "gāng dào",
    "english": "just arrived / just got here",
    "example_sentence": "我<b>刚到</b>家。",
    "sentence_pinyin": "",
    "sentence_translation": "",
    "hsk_level": 3,
    "source": "custom",
    "lesson": "2026",
    "notes": "",
    "created_at": "2026-04-29",
    "updated_at": "2026-04-29"
  },
  {
    "id": "custom-word-yiding",
    "hanzi": "一定",
    "pinyin": "yídìng",
    "english": "certainly / definitely",
    "example_sentence": "你<b>一定</b>要来。",
    "sentence_pinyin": "",
    "sentence_translation": "",
    "hsk_level": 2,
    "source": "custom",
    "lesson": "2026",
    "notes": "",
    "created_at": "2026-04-29",
    "updated_at": "2026-04-29"
  },
  {
    "id": "custom-word-keshi",
    "hanzi": "可是",
    "pinyin": "kěshì",
    "english": "but / however",
    "example_sentence": "我想去，<b>可是</b>今天没时间。",
    "sentence_pinyin": "",
    "sentence_translation": "",
    "hsk_level": 2,
    "source": "custom",
    "lesson": "2026",
    "notes": "",
    "created_at": "2026-04-29",
    "updated_at": "2026-04-29"
  },
  {
    "id": "custom-word-qing-zai-shuo-yi-bian",
    "hanzi": "请再说一遍",
    "pinyin": "qǐng zài shuō yí biàn",
    "english": "please say it again / please repeat that",
    "example_sentence": "我没听懂，<b>请再说一遍</b>。",
    "sentence_pinyin": "",
    "sentence_translation": "",
    "hsk_level": 3,
    "source": "custom",
    "lesson": "2026",
    "notes": "",
    "created_at": "2026-04-29",
    "updated_at": "2026-04-29"
  },
  {
    "id": "custom-word-wanju",
    "hanzi": "玩具",
    "pinyin": "wánjù",
    "english": "toy / toys",
    "example_sentence": "这个孩子很喜欢新<b>玩具</b>。",
    "sentence_pinyin": "",
    "sentence_translation": "",
    "hsk_level": 3,
    "source": "custom",
    "lesson": "2026",
    "notes": "",
    "created_at": "2026-04-29",
    "updated_at": "2026-04-29"
  },
  {
    "id": "custom-word-binggan",
    "hanzi": "饼干",
    "pinyin": "bǐnggān",
    "english": "cookies / biscuits",
    "example_sentence": "我早上吃了两块<b>饼干</b>。",
    "sentence_pinyin": "",
    "sentence_translation": "",
    "hsk_level": 3,
    "source": "custom",
    "lesson": "2026",
    "notes": "",
    "created_at": "2026-04-29",
    "updated_at": "2026-04-29"
  },
  {
    "id": "custom-word-qing-shuo-man-yidianr",
    "hanzi": "请说慢一点儿",
    "pinyin": "qǐng shuō màn yìdiǎnr",
    "english": "please speak a little more slowly",
    "example_sentence": "老师，<b>请说慢一点儿</b>。",
    "sentence_pinyin": "",
    "sentence_translation": "",
    "hsk_level": 3,
    "source": "custom",
    "lesson": "2026",
    "notes": "",
    "created_at": "2026-04-29",
    "updated_at": "2026-04-29"
  },
  {
    "id": "custom-word-lianxi",
    "hanzi": "练习",
    "pinyin": "liànxí",
    "english": "to practice / practice",
    "example_sentence": "我每天<b>练习</b>说中文。",
    "sentence_pinyin": "",
    "sentence_translation": "",
    "hsk_level": 2,
    "source": "custom",
    "lesson": "2026",
    "notes": "",
    "created_at": "2026-04-29",
    "updated_at": "2026-04-29"
  },
  {
    "id": "custom-word-fuqian",
    "hanzi": "付钱",
    "pinyin": "fùqián",
    "english": "to pay",
    "example_sentence": "今天我来<b>付钱</b>吧。",
    "sentence_pinyin": "",
    "sentence_translation": "",
    "hsk_level": 3,
    "source": "custom",
    "lesson": "2026",
    "notes": "",
    "created_at": "2026-04-29",
    "updated_at": "2026-04-29"
  },
  {
    "id": "custom-word-shou",
    "hanzi": "首",
    "pinyin": "shǒu",
    "english": "measure word for songs and poems",
    "example_sentence": "我很喜欢这<b>首</b>歌。",
    "sentence_pinyin": "",
    "sentence_translation": "",
    "hsk_level": 3,
    "source": "custom",
    "lesson": "2026",
    "notes": "",
    "created_at": "2026-04-29",
    "updated_at": "2026-04-29"
  },
  {
    "id": "custom-word-zhang",
    "hanzi": "张",
    "pinyin": "zhāng",
    "english": "measure word for flat things",
    "example_sentence": "我想买两<b>张</b>票。",
    "sentence_pinyin": "",
    "sentence_translation": "",
    "hsk_level": 2,
    "source": "custom",
    "lesson": "2026",
    "notes": "",
    "created_at": "2026-04-29",
    "updated_at": "2026-04-29"
  },
  {
    "id": "custom-word-liang",
    "hanzi": "辆",
    "pinyin": "liàng",
    "english": "measure word for vehicles",
    "example_sentence": "门口有一<b>辆</b>车。",
    "sentence_pinyin": "",
    "sentence_translation": "",
    "hsk_level": 3,
    "source": "custom",
    "lesson": "2026",
    "notes": "",
    "created_at": "2026-04-29",
    "updated_at": "2026-04-29"
  },
  {
    "id": "custom-word-shuang",
    "hanzi": "双",
    "pinyin": "shuāng",
    "english": "measure word for pairs",
    "example_sentence": "我买了一<b>双</b>鞋。",
    "sentence_pinyin": "",
    "sentence_translation": "",
    "hsk_level": 2,
    "source": "custom",
    "lesson": "2026",
    "notes": "",
    "created_at": "2026-04-29",
    "updated_at": "2026-04-29"
  },
  {
    "id": "custom-word-tai",
    "hanzi": "台",
    "pinyin": "tái",
    "english": "measure word for machines",
    "example_sentence": "我家有两<b>台</b>电脑。",
    "sentence_pinyin": "",
    "sentence_translation": "",
    "hsk_level": 3,
    "source": "custom",
    "lesson": "2026",
    "notes": "",
    "created_at": "2026-04-29",
    "updated_at": "2026-04-29"
  },
  {
    "id": "custom-word-ba",
    "hanzi": "把",
    "pinyin": "bǎ",
    "english": "measure word for objects with a handle",
    "example_sentence": "桌子上有一<b>把</b>伞。",
    "sentence_pinyin": "",
    "sentence_translation": "",
    "hsk_level": 3,
    "source": "custom",
    "lesson": "2026",
    "notes": "",
    "created_at": "2026-04-29",
    "updated_at": "2026-04-29"
  },
  {
    "id": "custom-word-huangse",
    "hanzi": "黄色",
    "pinyin": "huángsè",
    "english": "yellow",
    "example_sentence": "这件衣服是<b>黄色</b>的。",
    "sentence_pinyin": "",
    "sentence_translation": "",
    "hsk_level": 2,
    "source": "custom",
    "lesson": "2026",
    "notes": "",
    "created_at": "2026-04-29",
    "updated_at": "2026-04-29"
  },
  {
    "id": "custom-word-lanse",
    "hanzi": "蓝色",
    "pinyin": "lánsè",
    "english": "blue",
    "example_sentence": "我喜欢<b>蓝色</b>的书包。",
    "sentence_pinyin": "",
    "sentence_translation": "",
    "hsk_level": 2,
    "source": "custom",
    "lesson": "2026",
    "notes": "",
    "created_at": "2026-04-29",
    "updated_at": "2026-04-29"
  },
  {
    "id": "custom-word-chengse",
    "hanzi": "橙色",
    "pinyin": "chéngsè",
    "english": "orange",
    "example_sentence": "她买了一个<b>橙色</b>的杯子。",
    "sentence_pinyin": "",
    "sentence_translation": "",
    "hsk_level": 4,
    "source": "custom",
    "lesson": "2026",
    "notes": "",
    "created_at": "2026-04-29",
    "updated_at": "2026-04-29"
  },
  {
    "id": "custom-word-zise",
    "hanzi": "紫色",
    "pinyin": "zǐsè",
    "english": "purple",
    "example_sentence": "这朵花是<b>紫色</b>的。",
    "sentence_pinyin": "",
    "sentence_translation": "",
    "hsk_level": 4,
    "source": "custom",
    "lesson": "2026",
    "notes": "",
    "created_at": "2026-04-29",
    "updated_at": "2026-04-29"
  },
  {
    "id": "custom-word-fense",
    "hanzi": "粉色",
    "pinyin": "fěnsè",
    "english": "pink",
    "example_sentence": "她今天穿了<b>粉色</b>的裙子。",
    "sentence_pinyin": "",
    "sentence_translation": "",
    "hsk_level": 4,
    "source": "custom",
    "lesson": "2026",
    "notes": "",
    "created_at": "2026-04-29",
    "updated_at": "2026-04-29"
  },
  {
    "id": "custom-word-zongse",
    "hanzi": "棕色",
    "pinyin": "zōngsè",
    "english": "brown",
    "example_sentence": "我想买一双<b>棕色</b>的鞋。",
    "sentence_pinyin": "",
    "sentence_translation": "",
    "hsk_level": 4,
    "source": "custom",
    "lesson": "2026",
    "notes": "",
    "created_at": "2026-04-29",
    "updated_at": "2026-04-29"
  },
  {
    "id": "custom-word-huise",
    "hanzi": "灰色",
    "pinyin": "huīsè",
    "english": "gray",
    "example_sentence": "这只猫是<b>灰色</b>的。",
    "sentence_pinyin": "",
    "sentence_translation": "",
    "hsk_level": 4,
    "source": "custom",
    "lesson": "2026",
    "notes": "",
    "created_at": "2026-04-29",
    "updated_at": "2026-04-29"
  },
  {
    "id": "custom-word-yinyue",
    "hanzi": "音乐",
    "pinyin": "yīnyuè",
    "english": "music",
    "example_sentence": "我每天都听<b>音乐</b>。",
    "sentence_pinyin": "",
    "sentence_translation": "",
    "hsk_level": 2,
    "source": "custom",
    "lesson": "2026",
    "notes": "",
    "created_at": "2026-05-03",
    "updated_at": "2026-05-03"
  }
]
